{
  "items": [
    {
      "title": "Burrbery Jacke",
      "category": "jackets",
      "image": "/images/jackets/Burrbery_jacke.png",
      "price": 110,
      "sizes": []
    },
    {
      "title": "Crofton Steppjacke Canada Goose",
      "category": "jackets",
      "image": "/images/jackets/Crofton_Steppjacke_Canada_Goose.png",
      "price": 110,
      "sizes": []
    },
    {
      "title": "Moncler Karakorum Black",
      "category": "jackets",
      "image": "/images/jackets/Moncler_Karakorum_black.png",
      "price": 110,
      "sizes": []
    },
    {
      "title": "Moncler Karakorum Blue",
      "category": "jackets",
      "image": "/images/jackets/Moncler_Karakorum_blue.png",
      "price": 110,
      "sizes": []
    },
    {
      "title": "Moncler Karakorum Burgundered",
      "category": "jackets",
      "image": "/images/jackets/Moncler_Karakorum_burgundered.png",
      "price": 110,
      "sizes": []
    },
    {
      "title": "Moncler Karakorum Green",
      "category": "jackets",
      "image": "/images/jackets/Moncler_Karakorum_green.png",
      "price": 110,
      "sizes": []
    },
    {
      "title": "Moncler Karakorum Grey",
      "category": "jackets",
      "image": "/images/jackets/Moncler_Karakorum_grey.png",
      "price": 110,
      "sizes": []
    },
    {
      "title": "Moncler Maya Kurz Schwarz",
      "category": "jackets",
      "image": "/images/jackets/Moncler_Maya_kurz_schwarz.png",
      "price": 110,
      "sizes": []
    },
    {
      "title": "Moncler Maya Weiss",
      "category": "jackets",
      "image": "/images/jackets/Moncler_Maya_weiss.png",
      "price": 110,
      "sizes": []
    },
    {
      "title": "Prada Jacket Black",
      "category": "jackets",
      "image": "/images/jackets/Prada_jacket_black.png",
      "price": 110,
      "sizes": []
    },
    {
      "title": "Ralph Lauren Winter Jacket Black",
      "category": "jackets",
      "image": "/images/jackets/Ralph_Lauren_winter_jacket_black.png",
      "price": 110,
      "sizes": []
    },
    {
      "title": "Ralph Lauren Winter Jacket Dark Blue",
      "category": "jackets",
      "image": "/images/jackets/Ralph_Lauren_winter_jacket_dark_blue.png",
      "price": 110,
      "sizes": []
    },
    {
      "title": "Ralph Lauren Winter Jacket Red",
      "category": "jackets",
      "image": "/images/jackets/Ralph_Lauren_winter_jacket_red.png",
      "price": 110,
      "sizes": []
    },
    {
      "title": ". Polo Ralph Lauren Cable Knit Sweater Cream Navy Pony Logo",
      "category": "pullover",
      "image": "/images/pullover/._polo_ralph_lauren_cable_knit_sweater_cream_navy_pony_logo.jpg",
      "price": 60,
      "sizes": []
    },
    {
      "title": ". Stone Island Garment Dyed Sweatshirt Black",
      "category": "pullover",
      "image": "/images/pullover/._stone_island_garment_dyed_sweatshirt_black.jpg",
      "price": 60,
      "sizes": []
    },
    {
      "title": "Amie Pullover Black",
      "category": "pullover",
      "image": "/images/pullover/Amie_Pullover_black.png",
      "price": 60,
      "sizes": []
    },
    {
      "title": "Amie Pullover White",
      "category": "pullover",
      "image": "/images/pullover/Amie_Pullover_white.png",
      "price": 60,
      "sizes": []
    },
    {
      "title": "Burberry Pullover Black",
      "category": "pullover",
      "image": "/images/pullover/Burberry_Pullover_black.png",
      "price": 60,
      "sizes": []
    },
    {
      "title": "Burberry Pullover Blue",
      "category": "pullover",
      "image": "/images/pullover/Burberry_Pullover_blue.png",
      "price": 60,
      "sizes": []
    },
    {
      "title": "Burberry Pullover Grey",
      "category": "pullover",
      "image": "/images/pullover/Burberry_Pullover_grey.png",
      "price": 60,
      "sizes": []
    },
    {
      "title": "Burberry Pullover Nova Chek",
      "category": "pullover",
      "image": "/images/pullover/Burberry_Pullover_Nova_chek.png",
      "price": 60,
      "sizes": []
    },
    {
      "title": "Burberry Pullover Red",
      "category": "pullover",
      "image": "/images/pullover/Burberry_Pullover_red.png",
      "price": 60,
      "sizes": []
    },
    {
      "title": "Gucci Pullover Green",
      "category": "pullover",
      "image": "/images/pullover/Gucci_Pullover_green.png",
      "price": 60,
      "sizes": []
    },
    {
      "title": "Gucci Pullover Green Red",
      "category": "pullover",
      "image": "/images/pullover/Gucci_Pullover_green_red.png",
      "price": 60,
      "sizes": []
    },
    {
      "title": "Gucci Pullover Red",
      "category": "pullover",
      "image": "/images/pullover/Gucci_Pullover_red.png",
      "price": 60,
      "sizes": []
    },
    {
      "title": "Louis Vuitton Monogram",
      "category": "pullover",
      "image": "/images/pullover/Louis_Vuitton_Monogram.png",
      "price": 60,
      "sizes": []
    },
    {
      "title": "Louis Vuitton Monogram Black",
      "category": "pullover",
      "image": "/images/pullover/Louis_Vuitton_Monogram_black.png",
      "price": 60,
      "sizes": []
    },
    {
      "title": "Louis Vuitton Pre Owned Blue",
      "category": "pullover",
      "image": "/images/pullover/Louis_Vuitton_Pre-Owned_blue.png",
      "price": 60,
      "sizes": []
    },
    {
      "title": "Prada Hoodie Black",
      "category": "pullover",
      "image": "/images/pullover/Prada_Hoodie_black.png",
      "price": 60,
      "sizes": []
    },
    {
      "title": "Prada Pullover Black",
      "category": "pullover",
      "image": "/images/pullover/Prada_Pullover_black.png",
      "price": 60,
      "sizes": []
    },
    {
      "title": "Ralph Lauren Polo Black",
      "category": "pullover",
      "image": "/images/pullover/Ralph_Lauren_polo_black.png",
      "price": 60,
      "sizes": []
    },
    {
      "title": "Ralph Lauren Polo Blue",
      "category": "pullover",
      "image": "/images/pullover/Ralph_Lauren_polo_blue.png",
      "price": 60,
      "sizes": []
    },
    {
      "title": "Ralph Lauren Polo Dark Blue",
      "category": "pullover",
      "image": "/images/pullover/Ralph_Lauren_Polo_dark_blue.png",
      "price": 60,
      "sizes": []
    },
    {
      "title": "Ralph Lauren Polo Green",
      "category": "pullover",
      "image": "/images/pullover/Ralph_Lauren_polo_green.png",
      "price": 60,
      "sizes": []
    },
    {
      "title": "Ralph Lauren Polo White",
      "category": "pullover",
      "image": "/images/pullover/Ralph_Lauren_polo_white.png",
      "price": 60,
      "sizes": []
    },
    {
      "title": "Stone Island Pullover Black",
      "category": "pullover",
      "image": "/images/pullover/Stone_Island_Pullover_black.png",
      "price": 60,
      "sizes": []
    },
    {
      "title": "Stone Island Pullover White",
      "category": "pullover",
      "image": "/images/pullover/Stone_Island_Pullover_white.png",
      "price": 60,
      "sizes": []
    },
    {
      "title": "Stone Island Strcikpullover Blue",
      "category": "pullover",
      "image": "/images/pullover/Stone_Island_strcikpullover_blue.png",
      "price": 60,
      "sizes": []
    },
    {
      "title": "Stone Island Strcikpullover Grey",
      "category": "pullover",
      "image": "/images/pullover/Stone_Island_strcikpullover_grey.png",
      "price": 60,
      "sizes": []
    }
  ]
}